{"system":false,"name_i18n":{"en-US":"Skills"},"name":"Skills","listTypeEntries":[{"name_i18n":{"en-US":"Java"},"name":"Java","type":"","key":"Java","externalReferenceCode":"cab5a6d5-8583-9755-e5bd-a35db3b16b4b"},{"name_i18n":{"en-US":"FreeMarker"},"name":"FreeMarker","type":"","key":"FreeMarker","externalReferenceCode":"655907e3-86c3-aa2d-51ed-f55844481766"},{"name_i18n":{"en-US":"React"},"name":"React","type":"","key":"React","externalReferenceCode":"8d8f3c53-c835-9967-d10f-de272731fd3c"},{"name_i18n":{"en-US":"OSGi"},"name":"OSGi","type":"","key":"OSGi","externalReferenceCode":"aacc695a-5b1e-4431-3e5f-fe9b49bbedce"},{"name_i18n":{"en-US":"Jakarta"},"name":"Jakarta","type":"","key":"Jakarta","externalReferenceCode":"679db5de-5a01-6497-9afe-8d15524a4344"}],"externalReferenceCode":"db1c0b8d-6e0c-b770-6c98-a89b7ee2ee6e"}